{
"DICT_F_FLAG":"ITEM_FLAG",
"DICT_NAME_LAYER":"0",
"S_PUBLIC":"2",
"TABLE_SELECT":"",
"S_MTIME":"2012-12-10 22:38:03:171",
"TABLE_WHERE":" and dict_id='SY_COMM_TAG_GROUP'",
"SY_SERV_DICT_ITEM":
[
{
"ITEM_FIELD2":"",
"ITEM_FIELD1":"",
"S_PUBLIC":"1",
"ITEM_FLAG":"1",
"ITEM_IMG":"",
"_ROWNUM_":"0",
"CODE_PATH":"107^",
"ITEM_ORDER":"0",
"ITEM_ID":"CM_TAG_GROUP_40",
"ITEM_LEVEL":"1",
"_PK_":"CM_TAG_GROUP_40",
"S_CMPY":"ruaho",
"ITEM_NAME":"人事类",
"ITEM_PCODE":"0",
"ITEM_CODE":"107",
"ITEM_LEAF":"0",
"DICT_ID":"SY_COMM_TAG_GROUP"
},
{
"ITEM_FIELD2":"",
"ITEM_FIELD1":"",
"S_PUBLIC":"1",
"ITEM_FLAG":"1",
"ITEM_IMG":"",
"_ROWNUM_":"1",
"CODE_PATH":"1^",
"ITEM_ORDER":"1",
"ITEM_ID":"CM_TAG_GROUP_1",
"ITEM_LEVEL":"1",
"_PK_":"CM_TAG_GROUP_1",
"S_CMPY":"ruaho",
"ITEM_NAME":"管理类",
"ITEM_PCODE":"0",
"ITEM_CODE":"1",
"ITEM_LEAF":"0",
"DICT_ID":"SY_COMM_TAG_GROUP"
},
{
"ITEM_FIELD2":"",
"ITEM_FIELD1":"",
"S_PUBLIC":"1",
"ITEM_FLAG":"1",
"ITEM_IMG":"",
"_ROWNUM_":"2",
"CODE_PATH":"52^",
"ITEM_ORDER":"2",
"ITEM_ID":"CM_TAG_GROUP_6",
"ITEM_LEVEL":"1",
"_PK_":"CM_TAG_GROUP_6",
"S_CMPY":"ruaho",
"ITEM_NAME":"保险类",
"ITEM_PCODE":"0",
"ITEM_CODE":"52",
"ITEM_LEAF":"0",
"DICT_ID":"SY_COMM_TAG_GROUP"
},
{
"ITEM_FIELD2":"",
"ITEM_FIELD1":"",
"S_PUBLIC":"1",
"ITEM_FLAG":"1",
"ITEM_IMG":"",
"_ROWNUM_":"3",
"CODE_PATH":"53^",
"ITEM_ORDER":"3",
"ITEM_ID":"CM_TAG_GROUP_7",
"ITEM_LEVEL":"1",
"_PK_":"CM_TAG_GROUP_7",
"S_CMPY":"ruaho",
"ITEM_NAME":"资产管理类",
"ITEM_PCODE":"0",
"ITEM_CODE":"53",
"ITEM_LEAF":"0",
"DICT_ID":"SY_COMM_TAG_GROUP"
},
{
"ITEM_FIELD2":"",
"ITEM_FIELD1":"",
"S_PUBLIC":"1",
"ITEM_FLAG":"1",
"ITEM_IMG":"",
"_ROWNUM_":"4",
"CODE_PATH":"1^2^",
"ITEM_ORDER":"10",
"ITEM_ID":"CM_TAG_GROUP_2",
"ITEM_LEVEL":"2",
"_PK_":"CM_TAG_GROUP_2",
"S_CMPY":"ruaho",
"ITEM_NAME":"机构",
"ITEM_PCODE":"1",
"ITEM_CODE":"2",
"ITEM_LEAF":"0",
"DICT_ID":"SY_COMM_TAG_GROUP"
},
{
"ITEM_FIELD2":"",
"ITEM_FIELD1":"",
"S_PUBLIC":"1",
"ITEM_FLAG":"1",
"ITEM_IMG":"",
"_ROWNUM_":"5",
"CODE_PATH":"1^3^",
"ITEM_ORDER":"20",
"ITEM_ID":"CM_TAG_GROUP_3",
"ITEM_LEVEL":"2",
"_PK_":"CM_TAG_GROUP_3",
"S_CMPY":"ruaho",
"ITEM_NAME":"公司治理",
"ITEM_PCODE":"1",
"ITEM_CODE":"3",
"ITEM_LEAF":"0",
"DICT_ID":"SY_COMM_TAG_GROUP"
},
{
"ITEM_FIELD2":"",
"ITEM_FIELD1":"",
"S_PUBLIC":"1",
"ITEM_FLAG":"1",
"ITEM_IMG":"",
"_ROWNUM_":"6",
"CODE_PATH":"1^41^",
"ITEM_ORDER":"30",
"ITEM_ID":"CM_TAG_GROUP_4",
"ITEM_LEVEL":"2",
"_PK_":"CM_TAG_GROUP_4",
"S_CMPY":"ruaho",
"ITEM_NAME":"战略规划",
"ITEM_PCODE":"1",
"ITEM_CODE":"41",
"ITEM_LEAF":"0",
"DICT_ID":"SY_COMM_TAG_GROUP"
},
{
"ITEM_FIELD2":"",
"ITEM_FIELD1":"",
"S_PUBLIC":"1",
"ITEM_FLAG":"1",
"ITEM_IMG":"",
"_ROWNUM_":"7",
"CODE_PATH":"1^42^",
"ITEM_ORDER":"40",
"ITEM_ID":"CM_TAG_GROUP_5",
"ITEM_LEVEL":"2",
"_PK_":"CM_TAG_GROUP_5",
"S_CMPY":"ruaho",
"ITEM_NAME":"人力资源",
"ITEM_PCODE":"1",
"ITEM_CODE":"42",
"ITEM_LEAF":"0",
"DICT_ID":"SY_COMM_TAG_GROUP"
},
{
"ITEM_FIELD2":"",
"ITEM_FIELD1":"",
"S_PUBLIC":"1",
"ITEM_FLAG":"1",
"ITEM_IMG":"",
"_ROWNUM_":"8",
"CODE_PATH":"1^78^",
"ITEM_ORDER":"50",
"ITEM_ID":"CM_TAG_GROUP_31",
"ITEM_LEVEL":"2",
"_PK_":"CM_TAG_GROUP_31",
"S_CMPY":"ruaho",
"ITEM_NAME":"教育培训",
"ITEM_PCODE":"1",
"ITEM_CODE":"78",
"ITEM_LEAF":"0",
"DICT_ID":"SY_COMM_TAG_GROUP"
},
{
"ITEM_FIELD2":"",
"ITEM_FIELD1":"",
"S_PUBLIC":"1",
"ITEM_FLAG":"1",
"ITEM_IMG":"",
"_ROWNUM_":"9",
"CODE_PATH":"1^79^",
"ITEM_ORDER":"60",
"ITEM_ID":"CM_TAG_GROUP_32",
"ITEM_LEVEL":"2",
"_PK_":"CM_TAG_GROUP_32",
"S_CMPY":"ruaho",
"ITEM_NAME":"财务管理",
"ITEM_PCODE":"1",
"ITEM_CODE":"79",
"ITEM_LEAF":"0",
"DICT_ID":"SY_COMM_TAG_GROUP"
},
{
"ITEM_FIELD2":"",
"ITEM_FIELD1":"",
"S_PUBLIC":"1",
"ITEM_FLAG":"1",
"ITEM_IMG":"",
"_ROWNUM_":"10",
"CODE_PATH":"1^80^",
"ITEM_ORDER":"70",
"ITEM_ID":"CM_TAG_GROUP_33",
"ITEM_LEVEL":"2",
"_PK_":"CM_TAG_GROUP_33",
"S_CMPY":"ruaho",
"ITEM_NAME":"品牌宣传",
"ITEM_PCODE":"1",
"ITEM_CODE":"80",
"ITEM_LEAF":"0",
"DICT_ID":"SY_COMM_TAG_GROUP"
},
{
"ITEM_FIELD2":"",
"ITEM_FIELD1":"",
"S_PUBLIC":"1",
"ITEM_FLAG":"1",
"ITEM_IMG":"",
"_ROWNUM_":"11",
"CODE_PATH":"1^81^",
"ITEM_ORDER":"80",
"ITEM_ID":"CM_TAG_GROUP_34",
"ITEM_LEVEL":"2",
"_PK_":"CM_TAG_GROUP_34",
"S_CMPY":"ruaho",
"ITEM_NAME":"行政文秘",
"ITEM_PCODE":"1",
"ITEM_CODE":"81",
"ITEM_LEAF":"0",
"DICT_ID":"SY_COMM_TAG_GROUP"
},
{
"ITEM_FIELD2":"",
"ITEM_FIELD1":"",
"S_PUBLIC":"1",
"ITEM_FLAG":"1",
"ITEM_IMG":"",
"_ROWNUM_":"12",
"CODE_PATH":"1^82^",
"ITEM_ORDER":"90",
"ITEM_ID":"CM_TAG_GROUP_35",
"ITEM_LEVEL":"2",
"_PK_":"CM_TAG_GROUP_35",
"S_CMPY":"ruaho",
"ITEM_NAME":"信息技术",
"ITEM_PCODE":"1",
"ITEM_CODE":"82",
"ITEM_LEAF":"0",
"DICT_ID":"SY_COMM_TAG_GROUP"
},
{
"ITEM_FIELD2":"",
"ITEM_FIELD1":"",
"S_PUBLIC":"1",
"ITEM_FLAG":"1",
"ITEM_IMG":"",
"_ROWNUM_":"13",
"CODE_PATH":"1^83^",
"ITEM_ORDER":"100",
"ITEM_ID":"CM_TAG_GROUP_36",
"ITEM_LEVEL":"2",
"_PK_":"CM_TAG_GROUP_36",
"S_CMPY":"ruaho",
"ITEM_NAME":"审计内控",
"ITEM_PCODE":"1",
"ITEM_CODE":"83",
"ITEM_LEAF":"0",
"DICT_ID":"SY_COMM_TAG_GROUP"
},
{
"ITEM_FIELD2":"",
"ITEM_FIELD1":"",
"S_PUBLIC":"1",
"ITEM_FLAG":"1",
"ITEM_IMG":"",
"_ROWNUM_":"14",
"CODE_PATH":"1^84^",
"ITEM_ORDER":"110",
"ITEM_ID":"CM_TAG_GROUP_37",
"ITEM_LEVEL":"2",
"_PK_":"CM_TAG_GROUP_37",
"S_CMPY":"ruaho",
"ITEM_NAME":"法律合规",
"ITEM_PCODE":"1",
"ITEM_CODE":"84",
"ITEM_LEAF":"0",
"DICT_ID":"SY_COMM_TAG_GROUP"
},
{
"ITEM_FIELD2":"",
"ITEM_FIELD1":"",
"S_PUBLIC":"1",
"ITEM_FLAG":"1",
"ITEM_IMG":"",
"_ROWNUM_":"15",
"CODE_PATH":"1^85^",
"ITEM_ORDER":"120",
"ITEM_ID":"CM_TAG_GROUP_38",
"ITEM_LEVEL":"2",
"_PK_":"CM_TAG_GROUP_38",
"S_CMPY":"ruaho",
"ITEM_NAME":"纪检监察",
"ITEM_PCODE":"1",
"ITEM_CODE":"85",
"ITEM_LEAF":"0",
"DICT_ID":"SY_COMM_TAG_GROUP"
},
{
"ITEM_FIELD2":"",
"ITEM_FIELD1":"",
"S_PUBLIC":"1",
"ITEM_FLAG":"1",
"ITEM_IMG":"",
"_ROWNUM_":"16",
"CODE_PATH":"1^86^",
"ITEM_ORDER":"130",
"ITEM_ID":"CM_TAG_GROUP_39",
"ITEM_LEVEL":"2",
"_PK_":"CM_TAG_GROUP_39",
"S_CMPY":"ruaho",
"ITEM_NAME":"党群工作",
"ITEM_PCODE":"1",
"ITEM_CODE":"86",
"ITEM_LEAF":"0",
"DICT_ID":"SY_COMM_TAG_GROUP"
},
{
"ITEM_FIELD2":"",
"ITEM_FIELD1":"",
"S_PUBLIC":"1",
"ITEM_FLAG":"1",
"ITEM_IMG":"",
"_ROWNUM_":"17",
"CODE_PATH":"52^54^",
"ITEM_ORDER":"140",
"ITEM_ID":"CM_TAG_GROUP_8",
"ITEM_LEVEL":"2",
"_PK_":"CM_TAG_GROUP_8",
"S_CMPY":"ruaho",
"ITEM_NAME":"寿险产品",
"ITEM_PCODE":"52",
"ITEM_CODE":"54",
"ITEM_LEAF":"0",
"DICT_ID":"SY_COMM_TAG_GROUP"
},
{
"ITEM_FIELD2":"",
"ITEM_FIELD1":"",
"S_PUBLIC":"1",
"ITEM_FLAG":"1",
"ITEM_IMG":"",
"_ROWNUM_":"18",
"CODE_PATH":"52^55^",
"ITEM_ORDER":"150",
"ITEM_ID":"CM_TAG_GROUP_9",
"ITEM_LEVEL":"2",
"_PK_":"CM_TAG_GROUP_9",
"S_CMPY":"ruaho",
"ITEM_NAME":"财险产品",
"ITEM_PCODE":"52",
"ITEM_CODE":"55",
"ITEM_LEAF":"0",
"DICT_ID":"SY_COMM_TAG_GROUP"
},
{
"ITEM_FIELD2":"",
"ITEM_FIELD1":"",
"S_PUBLIC":"1",
"ITEM_FLAG":"1",
"ITEM_IMG":"",
"_ROWNUM_":"19",
"CODE_PATH":"52^56^",
"ITEM_ORDER":"160",
"ITEM_ID":"CM_TAG_GROUP_10",
"ITEM_LEVEL":"2",
"_PK_":"CM_TAG_GROUP_10",
"S_CMPY":"ruaho",
"ITEM_NAME":"企业年金",
"ITEM_PCODE":"52",
"ITEM_CODE":"56",
"ITEM_LEAF":"0",
"DICT_ID":"SY_COMM_TAG_GROUP"
},
{
"ITEM_FIELD2":"",
"ITEM_FIELD1":"",
"S_PUBLIC":"1",
"ITEM_FLAG":"1",
"ITEM_IMG":"",
"_ROWNUM_":"20",
"CODE_PATH":"52^57^",
"ITEM_ORDER":"170",
"ITEM_ID":"CM_TAG_GROUP_11",
"ITEM_LEVEL":"2",
"_PK_":"CM_TAG_GROUP_11",
"S_CMPY":"ruaho",
"ITEM_NAME":"精算",
"ITEM_PCODE":"52",
"ITEM_CODE":"57",
"ITEM_LEAF":"0",
"DICT_ID":"SY_COMM_TAG_GROUP"
},
{
"ITEM_FIELD2":"",
"ITEM_FIELD1":"",
"S_PUBLIC":"1",
"ITEM_FLAG":"1",
"ITEM_IMG":"",
"_ROWNUM_":"21",
"CODE_PATH":"52^58^",
"ITEM_ORDER":"180",
"ITEM_ID":"CM_TAG_GROUP_12",
"ITEM_LEVEL":"2",
"_PK_":"CM_TAG_GROUP_12",
"S_CMPY":"ruaho",
"ITEM_NAME":"产品管理",
"ITEM_PCODE":"52",
"ITEM_CODE":"58",
"ITEM_LEAF":"0",
"DICT_ID":"SY_COMM_TAG_GROUP"
},
{
"ITEM_FIELD2":"",
"ITEM_FIELD1":"",
"S_PUBLIC":"1",
"ITEM_FLAG":"1",
"ITEM_IMG":"",
"_ROWNUM_":"22",
"CODE_PATH":"52^59^",
"ITEM_ORDER":"190",
"ITEM_ID":"CM_TAG_GROUP_13",
"ITEM_LEVEL":"2",
"_PK_":"CM_TAG_GROUP_13",
"S_CMPY":"ruaho",
"ITEM_NAME":"销售管理",
"ITEM_PCODE":"52",
"ITEM_CODE":"59",
"ITEM_LEAF":"0",
"DICT_ID":"SY_COMM_TAG_GROUP"
},
{
"ITEM_FIELD2":"",
"ITEM_FIELD1":"",
"S_PUBLIC":"1",
"ITEM_FLAG":"1",
"ITEM_IMG":"",
"_ROWNUM_":"23",
"CODE_PATH":"52^60^",
"ITEM_ORDER":"200",
"ITEM_ID":"CM_TAG_GROUP_14",
"ITEM_LEVEL":"2",
"_PK_":"CM_TAG_GROUP_14",
"S_CMPY":"ruaho",
"ITEM_NAME":"个险销售",
"ITEM_PCODE":"52",
"ITEM_CODE":"60",
"ITEM_LEAF":"0",
"DICT_ID":"SY_COMM_TAG_GROUP"
},
{
"ITEM_FIELD2":"",
"ITEM_FIELD1":"",
"S_PUBLIC":"1",
"ITEM_FLAG":"1",
"ITEM_IMG":"",
"_ROWNUM_":"24",
"CODE_PATH":"52^61^",
"ITEM_ORDER":"210",
"ITEM_ID":"CM_TAG_GROUP_15",
"ITEM_LEVEL":"2",
"_PK_":"CM_TAG_GROUP_15",
"S_CMPY":"ruaho",
"ITEM_NAME":"团险销售",
"ITEM_PCODE":"52",
"ITEM_CODE":"61",
"ITEM_LEAF":"0",
"DICT_ID":"SY_COMM_TAG_GROUP"
},
{
"ITEM_FIELD2":"",
"ITEM_FIELD1":"",
"S_PUBLIC":"1",
"ITEM_FLAG":"1",
"ITEM_IMG":"",
"_ROWNUM_":"25",
"CODE_PATH":"52^62^",
"ITEM_ORDER":"220",
"ITEM_ID":"CM_TAG_GROUP_16",
"ITEM_LEVEL":"2",
"_PK_":"CM_TAG_GROUP_16",
"S_CMPY":"ruaho",
"ITEM_NAME":"银保销售",
"ITEM_PCODE":"52",
"ITEM_CODE":"62",
"ITEM_LEAF":"0",
"DICT_ID":"SY_COMM_TAG_GROUP"
},
{
"ITEM_FIELD2":"",
"ITEM_FIELD1":"",
"S_PUBLIC":"1",
"ITEM_FLAG":"1",
"ITEM_IMG":"",
"_ROWNUM_":"26",
"CODE_PATH":"52^63^",
"ITEM_ORDER":"230",
"ITEM_ID":"CM_TAG_GROUP_17",
"ITEM_LEVEL":"2",
"_PK_":"CM_TAG_GROUP_17",
"S_CMPY":"ruaho",
"ITEM_NAME":"电子商务",
"ITEM_PCODE":"52",
"ITEM_CODE":"63",
"ITEM_LEAF":"0",
"DICT_ID":"SY_COMM_TAG_GROUP"
},
{
"ITEM_FIELD2":"",
"ITEM_FIELD1":"",
"S_PUBLIC":"1",
"ITEM_FLAG":"1",
"ITEM_IMG":"",
"_ROWNUM_":"27",
"CODE_PATH":"52^64^",
"ITEM_ORDER":"240",
"ITEM_ID":"CM_TAG_GROUP_18",
"ITEM_LEVEL":"2",
"_PK_":"CM_TAG_GROUP_18",
"S_CMPY":"ruaho",
"ITEM_NAME":"业务管理",
"ITEM_PCODE":"52",
"ITEM_CODE":"64",
"ITEM_LEAF":"0",
"DICT_ID":"SY_COMM_TAG_GROUP"
},
{
"ITEM_FIELD2":"",
"ITEM_FIELD1":"",
"S_PUBLIC":"1",
"ITEM_FLAG":"1",
"ITEM_IMG":"",
"_ROWNUM_":"28",
"CODE_PATH":"52^65^",
"ITEM_ORDER":"250",
"ITEM_ID":"CM_TAG_GROUP_19",
"ITEM_LEVEL":"2",
"_PK_":"CM_TAG_GROUP_19",
"S_CMPY":"ruaho",
"ITEM_NAME":"客户服务",
"ITEM_PCODE":"52",
"ITEM_CODE":"65",
"ITEM_LEAF":"0",
"DICT_ID":"SY_COMM_TAG_GROUP"
},
{
"ITEM_FIELD2":"",
"ITEM_FIELD1":"",
"S_PUBLIC":"1",
"ITEM_FLAG":"1",
"ITEM_IMG":"",
"_ROWNUM_":"29",
"CODE_PATH":"53^66^",
"ITEM_ORDER":"260",
"ITEM_ID":"CM_TAG_GROUP_20",
"ITEM_LEVEL":"2",
"_PK_":"CM_TAG_GROUP_20",
"S_CMPY":"ruaho",
"ITEM_NAME":"资产管理",
"ITEM_PCODE":"53",
"ITEM_CODE":"66",
"ITEM_LEAF":"0",
"DICT_ID":"SY_COMM_TAG_GROUP"
},
{
"ITEM_FIELD2":"",
"ITEM_FIELD1":"",
"S_PUBLIC":"1",
"ITEM_FLAG":"1",
"ITEM_IMG":"",
"_ROWNUM_":"30",
"CODE_PATH":"53^67^",
"ITEM_ORDER":"270",
"ITEM_ID":"CM_TAG_GROUP_21",
"ITEM_LEVEL":"2",
"_PK_":"CM_TAG_GROUP_21",
"S_CMPY":"ruaho",
"ITEM_NAME":"交易管理",
"ITEM_PCODE":"53",
"ITEM_CODE":"67",
"ITEM_LEAF":"0",
"DICT_ID":"SY_COMM_TAG_GROUP"
},
{
"ITEM_FIELD2":"",
"ITEM_FIELD1":"",
"S_PUBLIC":"1",
"ITEM_FLAG":"1",
"ITEM_IMG":"",
"_ROWNUM_":"31",
"CODE_PATH":"53^68^",
"ITEM_ORDER":"280",
"ITEM_ID":"CM_TAG_GROUP_22",
"ITEM_LEVEL":"2",
"_PK_":"CM_TAG_GROUP_22",
"S_CMPY":"ruaho",
"ITEM_NAME":"项目投资",
"ITEM_PCODE":"53",
"ITEM_CODE":"68",
"ITEM_LEAF":"0",
"DICT_ID":"SY_COMM_TAG_GROUP"
},
{
"ITEM_FIELD2":"",
"ITEM_FIELD1":"",
"S_PUBLIC":"1",
"ITEM_FLAG":"1",
"ITEM_IMG":"",
"_ROWNUM_":"32",
"CODE_PATH":"53^69^",
"ITEM_ORDER":"290",
"ITEM_ID":"CM_TAG_GROUP_23",
"ITEM_LEVEL":"2",
"_PK_":"CM_TAG_GROUP_23",
"S_CMPY":"ruaho",
"ITEM_NAME":"证券投资",
"ITEM_PCODE":"53",
"ITEM_CODE":"69",
"ITEM_LEAF":"0",
"DICT_ID":"SY_COMM_TAG_GROUP"
},
{
"ITEM_FIELD2":"",
"ITEM_FIELD1":"",
"S_PUBLIC":"1",
"ITEM_FLAG":"1",
"ITEM_IMG":"",
"_ROWNUM_":"33",
"CODE_PATH":"53^70^",
"ITEM_ORDER":"300",
"ITEM_ID":"CM_TAG_GROUP_24",
"ITEM_LEVEL":"2",
"_PK_":"CM_TAG_GROUP_24",
"S_CMPY":"ruaho",
"ITEM_NAME":"固定收益投资",
"ITEM_PCODE":"53",
"ITEM_CODE":"70",
"ITEM_LEAF":"0",
"DICT_ID":"SY_COMM_TAG_GROUP"
},
{
"ITEM_FIELD2":"",
"ITEM_FIELD1":"",
"S_PUBLIC":"1",
"ITEM_FLAG":"1",
"ITEM_IMG":"",
"_ROWNUM_":"34",
"CODE_PATH":"53^71^",
"ITEM_ORDER":"310",
"ITEM_ID":"CM_TAG_GROUP_25",
"ITEM_LEVEL":"2",
"_PK_":"CM_TAG_GROUP_25",
"S_CMPY":"ruaho",
"ITEM_NAME":"基金投资",
"ITEM_PCODE":"53",
"ITEM_CODE":"71",
"ITEM_LEAF":"0",
"DICT_ID":"SY_COMM_TAG_GROUP"
},
{
"ITEM_FIELD2":"",
"ITEM_FIELD1":"",
"S_PUBLIC":"1",
"ITEM_FLAG":"1",
"ITEM_IMG":"",
"_ROWNUM_":"35",
"CODE_PATH":"53^72^",
"ITEM_ORDER":"320",
"ITEM_ID":"CM_TAG_GROUP_26",
"ITEM_LEVEL":"2",
"_PK_":"CM_TAG_GROUP_26",
"S_CMPY":"ruaho",
"ITEM_NAME":"股票投资",
"ITEM_PCODE":"53",
"ITEM_CODE":"72",
"ITEM_LEAF":"0",
"DICT_ID":"SY_COMM_TAG_GROUP"
},
{
"ITEM_FIELD2":"",
"ITEM_FIELD1":"",
"S_PUBLIC":"1",
"ITEM_FLAG":"1",
"ITEM_IMG":"",
"_ROWNUM_":"36",
"CODE_PATH":"53^73^",
"ITEM_ORDER":"330",
"ITEM_ID":"CM_TAG_GROUP_27",
"ITEM_LEVEL":"2",
"_PK_":"CM_TAG_GROUP_27",
"S_CMPY":"ruaho",
"ITEM_NAME":"国际业务",
"ITEM_PCODE":"53",
"ITEM_CODE":"73",
"ITEM_LEAF":"0",
"DICT_ID":"SY_COMM_TAG_GROUP"
},
{
"ITEM_FIELD2":"",
"ITEM_FIELD1":"",
"S_PUBLIC":"1",
"ITEM_FLAG":"1",
"ITEM_IMG":"",
"_ROWNUM_":"37",
"CODE_PATH":"53^74^",
"ITEM_ORDER":"340",
"ITEM_ID":"CM_TAG_GROUP_28",
"ITEM_LEVEL":"2",
"_PK_":"CM_TAG_GROUP_28",
"S_CMPY":"ruaho",
"ITEM_NAME":"机构业务",
"ITEM_PCODE":"53",
"ITEM_CODE":"74",
"ITEM_LEAF":"0",
"DICT_ID":"SY_COMM_TAG_GROUP"
},
{
"ITEM_FIELD2":"",
"ITEM_FIELD1":"",
"S_PUBLIC":"1",
"ITEM_FLAG":"1",
"ITEM_IMG":"",
"_ROWNUM_":"38",
"CODE_PATH":"53^75^",
"ITEM_ORDER":"350",
"ITEM_ID":"CM_TAG_GROUP_29",
"ITEM_LEVEL":"2",
"_PK_":"CM_TAG_GROUP_29",
"S_CMPY":"ruaho",
"ITEM_NAME":"账户管理",
"ITEM_PCODE":"53",
"ITEM_CODE":"75",
"ITEM_LEAF":"0",
"DICT_ID":"SY_COMM_TAG_GROUP"
},
{
"ITEM_FIELD2":"",
"ITEM_FIELD1":"",
"S_PUBLIC":"1",
"ITEM_FLAG":"1",
"ITEM_IMG":"",
"_ROWNUM_":"39",
"CODE_PATH":"53^76^",
"ITEM_ORDER":"360",
"ITEM_ID":"CM_TAG_GROUP_30",
"ITEM_LEVEL":"2",
"_PK_":"CM_TAG_GROUP_30",
"S_CMPY":"ruaho",
"ITEM_NAME":"投资研究",
"ITEM_PCODE":"53",
"ITEM_CODE":"76",
"ITEM_LEAF":"0",
"DICT_ID":"SY_COMM_TAG_GROUP"
}
],
"DICT_DIS_FORMAT":"",
"PRO_FLAG":"1",
"DICT_TYPE":"2",
"DICT_SRC_ID":"",
"TABLE_ID":"SY_DICT_ITEM",
"DICT_F_NAME":"ITEM_NAME",
"DICT_NAME":"标签分组",
"DICT_DATA_SOURCE":"",
"DICT_F_LEAF":"",
"DICT_IS_INNER":"2",
"DICT_ID":"SY_COMM_TAG_GROUP",
"S_FLAG":"1",
"DICT_LOAD_TYPE":"1",
"DICT_EXPRESSION":"",
"_ROWNUM_":"0",
"DICT_ROOT":"",
"DICT_F_PATH":"CODE_PATH",
"DICT_DIS_LAYER":"0",
"DICT_F_PARENT":"ITEM_PCODE",
"TABLE_ORDER":"ITEM_ORDER",
"_PK_":"SY_COMM_TAG_GROUP",
"DICT_F_LEVEL":"ITEM_LEVEL",
"DICT_CHILD_ID":"",
"DICT_F_CMPY":"S_CMPY",
"S_CMPY":"ruaho",
"DICT_F_ID":"ITEM_CODE"
}