{
"SERV_ID":"SY_COMM_ENTITY_ZHUBAN",
"SERV_QUERY_MODE":"1",
"SERV_WF_FLAG":"0",
"SERV_DELETE_FLAG":"2",
"S_PUBLIC":"1",
"SERV_PAGE_COUNT":"50",
"SERV_PID":"SY_COMM_ENTITY_STATE",
"SERV_SEARCH_FLAG":"2",
"SERV_TYPE":"1",
"SERV_CMPY":"",
"SERV_NAME":"主办事务",
"SERV_CLASS":"com.rh.core.comm.entity.EntityZhuBan",
"SERV_SRC_ID":"",
"S_USER":"yuananan",
"SERV_RED_HEAD":"",
"SERV_MOBILE_LIST":"",
"_ROWNUM_":"0",
"SERV_SQL_WHERE":" AND S_FLAG = 1 and QUERY_ODEPT = '@ODEPT_CODE@'",
"SERV_NAV_ITEMS":"",
"TABLE_ACTION":"",
"SERV_DATA_SOURCE":"",
"SERV_CARD_STYLE":"2",
"SERV_CARD_TMPL":"",
"SY_SERV_ACT":
[
],
"SERV_KEYS":"",
"SERV_LIST_STYLE":"",
"S_MTIME":"2013-05-31 18:12:26:964",
"PRO_FLAG":"1",
"SERV_MEMO":"",
"SERV_DATA_TITLE":"",
"SERV_AUTH_FLAG":"1",
"SERV_JS":"",
"SERV_CARD_LOAD":"2",
"SERV_NO_COUNT":"2",
"SERV_LOCK_FLAG":"2",
"SERV_SQL_ORDER":"S_EMERGENCY desc,S_MTIME desc",
"SERV_FILE_PATH":"",
"SY_SERV_LINK":
[
],
"S_FLAG":"1",
"TABLE_VIEW":"",
"SY_SERV_ITEM":
[
],
"SY_SERV_QUERY":
[
],
"SERV_CACHE_FLAG":"3",
"_PK_":"SY_COMM_ENTITY_ZHUBAN",
"SERV_LIST_LOAD":"2",
"S_CMPY":"ruaho",
"SERV_DATA_CODE":"",
"SERV_DICT_CACHE":"",
"SERV_CARD_TMPL_CODES":"",
"SY_SERV_WHERE":
[
]
}