{
"SERV_ID":"TS_XMGL_BMSH_SHGZ_MX",
"SERV_QUERY_MODE":"1",
"SERV_WF_FLAG":"0",
"SERV_DELETE_FLAG":"2",
"S_PUBLIC":"1",
"SERV_PAGE_COUNT":"50",
"SERV_PID":"",
"SERV_SEARCH_FLAG":"2",
"SERV_TYPE":"1",
"SERV_CMPY":"",
"SERV_NAME":"报名审核规则明细",
"SERV_CLASS":"com.rh.ts.bmsh.shgz.MxServ",
"SERV_SRC_ID":"",
"SERV_EXPTENDS":"",
"S_USER":"278p246BZ2jNaftzl7kooot",
"SERV_RED_HEAD":"",
"TODO_TYPE":"",
"SERV_MOBILE_LIST":"",
"_ROWNUM_":"0",
"EN_JSON":"",
"SERV_SQL_WHERE":"AND S_FLAG=1",
"SERV_NAV_ITEMS":"",
"TABLE_ACTION":"TS_XMGL_BMSH_SHGZ_MX",
"SERV_DATA_SOURCE":"",
"SERV_CARD_STYLE":"2",
"SY_SERV_ACT":
[
{
"SERV_ID":"TS_XMGL_BMSH_SHGZ_MX",
"ACT_WS_RESULT":"",
"S_FLAG":"1",
"ACT_LOG_FLAG":"2",
"ACT_ID":"2o6Ig9EnldEa2062Du5G",
"ACT_HOT_KEY":"",
"S_MTIME":"2017-07-28 17:29:49:978",
"_ROWNUM_":"0",
"EN_JSON":"",
"ACT_TYPE":"3",
"ACT_TIP":"",
"_PK_":"2o6Ig9EnldEa2062Du5G",
"ACT_WS_FLAG":"2",
"ACT_GROUP":"2",
"ACT_CSS":"byid",
"ACT_NAME":" 查 看 ",
"ACT_EXPRESSION":"",
"ACT_MEMO":"",
"SY_SERV_ACT_PARAM":
[
],
"ACT_ORDER":"10",
"ACT_MOBILE_FLAG":"1",
"ACT_CODE":"byid",
"ACT_EXPRESSION_FLAG":""
},
{
"SERV_ID":"TS_XMGL_BMSH_SHGZ_MX",
"ACT_WS_RESULT":"",
"S_FLAG":"1",
"ACT_LOG_FLAG":"2",
"ACT_ID":"2DaiAF4KB5Zrh8PrGrAy",
"ACT_HOT_KEY":"",
"S_MTIME":"2017-07-28 17:29:50:669",
"_ROWNUM_":"1",
"EN_JSON":"",
"ACT_TYPE":"3",
"ACT_TIP":"确保列表无编辑组按钮卡片也可以保存",
"_PK_":"2DaiAF4KB5Zrh8PrGrAy",
"ACT_WS_FLAG":"2",
"ACT_GROUP":"1",
"ACT_CSS":"exp",
"ACT_NAME":"修改",
"ACT_EXPRESSION":"",
"ACT_MEMO":"",
"SY_SERV_ACT_PARAM":
[
],
"ACT_ORDER":"15",
"ACT_MOBILE_FLAG":"1",
"ACT_CODE":"modify",
"ACT_EXPRESSION_FLAG":""
},
{
"SERV_ID":"TS_XMGL_BMSH_SHGZ_MX",
"ACT_WS_RESULT":"",
"S_FLAG":"1",
"ACT_LOG_FLAG":"2",
"ACT_ID":"1767oRFEFd5qQTyM0ILn",
"ACT_HOT_KEY":"",
"S_MTIME":"2017-11-15 15:30:49:272",
"_ROWNUM_":"2",
"EN_JSON":"",
"ACT_TYPE":"1",
"ACT_TIP":"",
"_PK_":"1767oRFEFd5qQTyM0ILn",
"ACT_WS_FLAG":"2",
"ACT_GROUP":"1",
"ACT_CSS":"add",
"ACT_NAME":" 添 加 ",
"ACT_EXPRESSION":"",
"ACT_MEMO":"",
"SY_SERV_ACT_PARAM":
[
],
"ACT_ORDER":"20",
"ACT_MOBILE_FLAG":"1",
"ACT_CODE":"add",
"ACT_EXPRESSION_FLAG":""
},
{
"SERV_ID":"TS_XMGL_BMSH_SHGZ_MX",
"ACT_WS_RESULT":"",
"S_FLAG":"2",
"ACT_LOG_FLAG":"2",
"ACT_ID":"0kRo4yaFt6pUtqj8YgHY",
"ACT_HOT_KEY":"",
"S_MTIME":"2017-07-28 17:29:50:025",
"_ROWNUM_":"3",
"EN_JSON":"",
"ACT_TYPE":"1",
"ACT_TIP":"",
"_PK_":"0kRo4yaFt6pUtqj8YgHY",
"ACT_WS_FLAG":"2",
"ACT_GROUP":"1",
"ACT_CSS":"batchSave",
"ACT_NAME":" 保 存 ",
"ACT_EXPRESSION":"",
"ACT_MEMO":"",
"SY_SERV_ACT_PARAM":
[
],
"ACT_ORDER":"30",
"ACT_MOBILE_FLAG":"1",
"ACT_CODE":"batchSave",
"ACT_EXPRESSION_FLAG":""
},
{
"SERV_ID":"TS_XMGL_BMSH_SHGZ_MX",
"ACT_WS_RESULT":"",
"S_FLAG":"1",
"ACT_LOG_FLAG":"2",
"ACT_ID":"3fxQs7taR2f9SIWhvEHz",
"ACT_HOT_KEY":"",
"S_MTIME":"2017-07-28 17:29:50:236",
"_ROWNUM_":"4",
"EN_JSON":"",
"ACT_TYPE":"2",
"ACT_TIP":"",
"_PK_":"3fxQs7taR2f9SIWhvEHz",
"ACT_WS_FLAG":"2",
"ACT_GROUP":"1",
"ACT_CSS":"save",
"ACT_NAME":" 保 存 ",
"ACT_EXPRESSION":"",
"ACT_MEMO":"",
"SY_SERV_ACT_PARAM":
[
],
"ACT_ORDER":"50",
"ACT_MOBILE_FLAG":"1",
"ACT_CODE":"save",
"ACT_EXPRESSION_FLAG":""
},
{
"SERV_ID":"TS_XMGL_BMSH_SHGZ_MX",
"ACT_WS_RESULT":"",
"S_FLAG":"2",
"ACT_LOG_FLAG":"2",
"ACT_ID":"3elQfyIBJ1gFWjt1CvtJ",
"ACT_HOT_KEY":"",
"S_MTIME":"2017-07-28 17:29:50:296",
"_ROWNUM_":"5",
"EN_JSON":"",
"ACT_TYPE":"2",
"ACT_TIP":"",
"_PK_":"3elQfyIBJ1gFWjt1CvtJ",
"ACT_WS_FLAG":"2",
"ACT_GROUP":"1",
"ACT_CSS":"copy",
"ACT_NAME":"复制并新建",
"ACT_EXPRESSION":"'#_ADD_#'==''",
"ACT_MEMO":"",
"SY_SERV_ACT_PARAM":
[
],
"ACT_ORDER":"60",
"ACT_MOBILE_FLAG":"1",
"ACT_CODE":"copyNew",
"ACT_EXPRESSION_FLAG":""
},
{
"SERV_ID":"TS_XMGL_BMSH_SHGZ_MX",
"ACT_WS_RESULT":"",
"S_FLAG":"2",
"ACT_LOG_FLAG":"2",
"ACT_ID":"37b7VDud503aySlDcj21",
"ACT_HOT_KEY":"",
"S_MTIME":"2017-07-28 17:29:50:356",
"_ROWNUM_":"6",
"EN_JSON":"",
"ACT_TYPE":"2",
"ACT_TIP":"",
"_PK_":"37b7VDud503aySlDcj21",
"ACT_WS_FLAG":"2",
"ACT_GROUP":"2",
"ACT_CSS":"search",
"ACT_NAME":"变更历史",
"ACT_EXPRESSION":"'#_ADD_#'==''",
"ACT_MEMO":"",
"SY_SERV_ACT_PARAM":
[
],
"ACT_ORDER":"70",
"ACT_MOBILE_FLAG":"1",
"ACT_CODE":"logItem",
"ACT_EXPRESSION_FLAG":""
},
{
"SERV_ID":"TS_XMGL_BMSH_SHGZ_MX",
"ACT_WS_RESULT":"",
"S_FLAG":"1",
"ACT_LOG_FLAG":"1",
"ACT_ID":"3TNWWr6J717bbCZH3zH2",
"ACT_HOT_KEY":"",
"S_MTIME":"2017-07-28 17:29:50:079",
"_ROWNUM_":"7",
"EN_JSON":"",
"ACT_TYPE":"1",
"ACT_TIP":"",
"_PK_":"3TNWWr6J717bbCZH3zH2",
"ACT_WS_FLAG":"2",
"ACT_GROUP":"1",
"ACT_CSS":"delete",
"ACT_NAME":" 删 除 ",
"ACT_EXPRESSION":"",
"ACT_MEMO":"",
"SY_SERV_ACT_PARAM":
[
],
"ACT_ORDER":"100",
"ACT_MOBILE_FLAG":"1",
"ACT_CODE":"delete",
"ACT_EXPRESSION_FLAG":""
},
{
"SERV_ID":"TS_XMGL_BMSH_SHGZ_MX",
"ACT_WS_RESULT":"",
"S_FLAG":"2",
"ACT_LOG_FLAG":"2",
"ACT_ID":"2k39j8qOZf4raOR9yb5K",
"ACT_HOT_KEY":"",
"S_MTIME":"2017-07-28 17:29:50:178",
"_ROWNUM_":"8",
"EN_JSON":"",
"ACT_TYPE":"1",
"ACT_TIP":"",
"_PK_":"2k39j8qOZf4raOR9yb5K",
"ACT_WS_FLAG":"2",
"ACT_GROUP":"1",
"ACT_CSS":"imp",
"ACT_NAME":" 导 入 ",
"ACT_EXPRESSION":"",
"ACT_MEMO":"",
"SY_SERV_ACT_PARAM":
[
],
"ACT_ORDER":"110",
"ACT_MOBILE_FLAG":"1",
"ACT_CODE":"imp",
"ACT_EXPRESSION_FLAG":""
},
{
"SERV_ID":"TS_XMGL_BMSH_SHGZ_MX",
"ACT_WS_RESULT":"",
"S_FLAG":"2",
"ACT_LOG_FLAG":"2",
"ACT_ID":"0RhJLZIJd6aajgcvo4MD",
"ACT_HOT_KEY":"",
"S_MTIME":"2017-07-28 17:29:50:126",
"_ROWNUM_":"9",
"EN_JSON":"",
"ACT_TYPE":"1",
"ACT_TIP":"",
"_PK_":"0RhJLZIJd6aajgcvo4MD",
"ACT_WS_FLAG":"2",
"ACT_GROUP":"2",
"ACT_CSS":"exp",
"ACT_NAME":" 导 出 ",
"ACT_EXPRESSION":"",
"ACT_MEMO":"@{\"_SELECT_\":\"*\"}",
"SY_SERV_ACT_PARAM":
[
],
"ACT_ORDER":"120",
"ACT_MOBILE_FLAG":"1",
"ACT_CODE":"exp",
"ACT_EXPRESSION_FLAG":""
},
{
"SERV_ID":"TS_XMGL_BMSH_SHGZ_MX",
"ACT_WS_RESULT":"",
"S_FLAG":"2",
"ACT_LOG_FLAG":"2",
"ACT_ID":"1BNu3OYjX9btqZcckLEw",
"ACT_HOT_KEY":"",
"S_MTIME":"2017-07-28 17:29:50:427",
"_ROWNUM_":"10",
"EN_JSON":"",
"ACT_TYPE":"2",
"ACT_TIP":"",
"_PK_":"1BNu3OYjX9btqZcckLEw",
"ACT_WS_FLAG":"2",
"ACT_GROUP":"2",
"ACT_CSS":"exp",
"ACT_NAME":" 接 收 ",
"ACT_EXPRESSION":"",
"ACT_MEMO":"this.receive();",
"SY_SERV_ACT_PARAM":
[
],
"ACT_ORDER":"130",
"ACT_MOBILE_FLAG":"1",
"ACT_CODE":"receive",
"ACT_EXPRESSION_FLAG":""
},
{
"SERV_ID":"TS_XMGL_BMSH_SHGZ_MX",
"ACT_WS_RESULT":"",
"S_FLAG":"2",
"ACT_LOG_FLAG":"2",
"ACT_ID":"18c4moC2l3bapFECTv0e",
"ACT_HOT_KEY":"",
"S_MTIME":"2017-07-28 17:29:50:502",
"_ROWNUM_":"11",
"EN_JSON":"",
"ACT_TYPE":"1",
"ACT_TIP":"zip文件导入",
"_PK_":"18c4moC2l3bapFECTv0e",
"ACT_WS_FLAG":"2",
"ACT_GROUP":"1",
"ACT_CSS":"imp",
"ACT_NAME":"批量导入",
"ACT_EXPRESSION":"",
"ACT_MEMO":"",
"SY_SERV_ACT_PARAM":
[
],
"ACT_ORDER":"140",
"ACT_MOBILE_FLAG":"1",
"ACT_CODE":"impZip",
"ACT_EXPRESSION_FLAG":""
},
{
"SERV_ID":"TS_XMGL_BMSH_SHGZ_MX",
"ACT_WS_RESULT":"",
"S_FLAG":"2",
"ACT_LOG_FLAG":"2",
"ACT_ID":"2bK7gCkU4ZewFeajVEvI",
"ACT_HOT_KEY":"",
"S_MTIME":"2017-07-28 17:29:50:581",
"_ROWNUM_":"12",
"EN_JSON":"",
"ACT_TYPE":"1",
"ACT_TIP":"zip文件导出",
"_PK_":"2bK7gCkU4ZewFeajVEvI",
"ACT_WS_FLAG":"2",
"ACT_GROUP":"2",
"ACT_CSS":"imp",
"ACT_NAME":"批量导出",
"ACT_EXPRESSION":"",
"ACT_MEMO":"",
"SY_SERV_ACT_PARAM":
[
],
"ACT_ORDER":"150",
"ACT_MOBILE_FLAG":"1",
"ACT_CODE":"expZip",
"ACT_EXPRESSION_FLAG":""
}
],
"SERV_CARD_TMPL":"",
"SERV_KEYS":"MX_ID",
"SERV_LIST_STYLE":"",
"S_MTIME":"2017-11-21 15:40:48:776",
"PRO_FLAG":"1",
"SERV_MEMO":"项目管理报名审核审核规则库明细",
"SERV_DATA_TITLE":"",
"SERV_AUTH_FLAG":"1",
"SERV_JS":"",
"SERV_CARD_LOAD":"1",
"SERV_NO_COUNT":"0",
"SERV_LOCK_FLAG":"2",
"SERV_SQL_ORDER":"MX_SORT",
"SERV_MOBILE_JS":"",
"SERV_FILE_PATH":"",
"SY_SERV_LINK":
[
],
"S_FLAG":"1",
"SAFE_FLAG":"0",
"TABLE_VIEW":"TS_XMGL_BMSH_SHGZ_MX",
"SY_SERV_QUERY":
[
],
"SY_SERV_ITEM":
[
{
"SERV_ID":"TS_XMGL_BMSH_SHGZ_MX",
"ITEM_CARD_WIDTH":"0",
"ITEM_LOG_FLAG":"2",
"ITEM_TIP":"",
"ITEM_ORDER_CODES":"",
"ITEM_CARD_FORMAT":"",
"ITEM_LIST_STYLE":"",
"ITEM_VALIDATE":"",
"ITEM_MEMO":"主键id",
"ITEM_VALIDATE_HINT":"",
"ITEM_NOTNULL":"1",
"ITEM_LIST_ORDER":"0",
"ITEM_FIELD_TYPE":"STR",
"SAFE_HTML":"",
"ITEM_SEARCH_FLAG":"1",
"ITEM_INPUT_MODE":"1",
"ITEM_USER_FLAG":"0",
"_ROWNUM_":"0",
"EN_JSON":"",
"ITEM_LIST_WIDTH":"0",
"ITEM_EXPTENDS":"",
"ITEM_NAME":"主键id",
"ITEM_NOTNULL_SCRIPT":"",
"ITEM_CARD_ORDER":"",
"ITEM_CARD_COLS":"1",
"ITEM_SUM_FLAG":"0",
"ITEM_TYPE":"1",
"S_MTIME":"2017-08-21 14:53:29:184",
"ITEM_LIST_FORMAT":"",
"ITEM_ID":"1Gfstl6CdeJUM2r2RT9f",
"ITEM_LIST_FLAG":"3",
"ITEM_CARD_DISABLE":"2",
"ITEM_CARD_ROWS":"1",
"ITEM_READONLY":"2",
"ITEM_HIDDEN_SCRIPT":"",
"ITEM_LIST_EDIT":"2",
"DICT_ID":"",
"ITEM_READONLY_SCRIPT":"",
"ITEM_FIELD_LENGTH":"40",
"S_FLAG":"1",
"ITEM_CARD_LINK":"",
"ITEM_HIDDEN":"1",
"ITEM_CARD_STYLE":"",
"ITEM_UNIQUE_GROUP":"0",
"_PK_":"1Gfstl6CdeJUM2r2RT9f",
"ITEM_LIST_ALIGN":"1",
"ITEM_INPUT_TYPE":"1",
"ITEM_LIST_LINK":"",
"ITEM_INPUT_FLAG":"2",
"ITEM_LABEL_HIDDEN":"0",
"ITEM_CODE":"MX_ID",
"ITEM_MOBILE_TYPE":"3",
"ITEM_INPUT_DEFAULT":"",
"ITEM_INPUT_CONFIG":""
},
{
"SERV_ID":"TS_XMGL_BMSH_SHGZ_MX",
"ITEM_CARD_WIDTH":"0",
"ITEM_LOG_FLAG":"2",
"ITEM_TIP":"",
"ITEM_ORDER_CODES":"",
"ITEM_CARD_FORMAT":"",
"ITEM_LIST_STYLE":"",
"ITEM_VALIDATE":"",
"ITEM_MEMO":"规则id",
"ITEM_VALIDATE_HINT":"",
"ITEM_NOTNULL":"2",
"ITEM_LIST_ORDER":"10",
"ITEM_FIELD_TYPE":"STR",
"SAFE_HTML":"",
"ITEM_SEARCH_FLAG":"1",
"ITEM_INPUT_MODE":"1",
"ITEM_USER_FLAG":"0",
"_ROWNUM_":"1",
"EN_JSON":"",
"ITEM_LIST_WIDTH":"0",
"ITEM_EXPTENDS":"",
"ITEM_NAME":"规则id",
"ITEM_NOTNULL_SCRIPT":"",
"ITEM_CARD_ORDER":"",
"ITEM_CARD_COLS":"1",
"ITEM_SUM_FLAG":"0",
"ITEM_TYPE":"1",
"S_MTIME":"2017-11-15 15:28:25:574",
"ITEM_LIST_FORMAT":"",
"ITEM_ID":"0xnZmIvre93dWhDNtmAe",
"ITEM_LIST_FLAG":"3",
"ITEM_CARD_DISABLE":"2",
"ITEM_CARD_ROWS":"1",
"ITEM_READONLY":"2",
"ITEM_HIDDEN_SCRIPT":"",
"ITEM_LIST_EDIT":"2",
"DICT_ID":"",
"ITEM_READONLY_SCRIPT":"",
"ITEM_FIELD_LENGTH":"40",
"S_FLAG":"1",
"ITEM_CARD_LINK":"",
"ITEM_HIDDEN":"1",
"ITEM_CARD_STYLE":"",
"ITEM_UNIQUE_GROUP":"0",
"_PK_":"0xnZmIvre93dWhDNtmAe",
"ITEM_LIST_ALIGN":"1",
"ITEM_INPUT_TYPE":"1",
"ITEM_LIST_LINK":"",
"ITEM_INPUT_FLAG":"2",
"ITEM_LABEL_HIDDEN":"0",
"ITEM_CODE":"GZ_ID",
"ITEM_MOBILE_TYPE":"3",
"ITEM_INPUT_DEFAULT":"",
"ITEM_INPUT_CONFIG":""
},
{
"SERV_ID":"TS_XMGL_BMSH_SHGZ_MX",
"ITEM_CARD_WIDTH":"0",
"ITEM_LOG_FLAG":"2",
"ITEM_TIP":"",
"ITEM_ORDER_CODES":"",
"ITEM_CARD_FORMAT":"",
"ITEM_LIST_STYLE":"",
"ITEM_VALIDATE":"",
"ITEM_MEMO":"名称",
"ITEM_VALIDATE_HINT":"",
"ITEM_NOTNULL":"2",
"ITEM_LIST_ORDER":"20",
"ITEM_FIELD_TYPE":"STR",
"SAFE_HTML":"",
"ITEM_SEARCH_FLAG":"1",
"ITEM_INPUT_MODE":"1",
"ITEM_USER_FLAG":"0",
"_ROWNUM_":"2",
"EN_JSON":"",
"ITEM_LIST_WIDTH":"0",
"ITEM_EXPTENDS":"",
"ITEM_NAME":"名称",
"ITEM_NOTNULL_SCRIPT":"",
"ITEM_CARD_ORDER":"",
"ITEM_CARD_COLS":"1",
"ITEM_SUM_FLAG":"0",
"ITEM_TYPE":"1",
"S_MTIME":"2017-07-31 15:01:32:054",
"ITEM_LIST_FORMAT":"",
"ITEM_ID":"01sJGlGrFeVXhdpvaAHf",
"ITEM_LIST_FLAG":"1",
"ITEM_CARD_DISABLE":"2",
"ITEM_CARD_ROWS":"1",
"ITEM_READONLY":"2",
"ITEM_HIDDEN_SCRIPT":"",
"ITEM_LIST_EDIT":"2",
"DICT_ID":"",
"ITEM_READONLY_SCRIPT":"",
"ITEM_FIELD_LENGTH":"40",
"S_FLAG":"1",
"ITEM_CARD_LINK":"",
"ITEM_HIDDEN":"2",
"ITEM_CARD_STYLE":"",
"ITEM_UNIQUE_GROUP":"0",
"_PK_":"01sJGlGrFeVXhdpvaAHf",
"ITEM_LIST_ALIGN":"1",
"ITEM_INPUT_TYPE":"1",
"ITEM_LIST_LINK":"",
"ITEM_INPUT_FLAG":"2",
"ITEM_LABEL_HIDDEN":"0",
"ITEM_CODE":"MX_NAME",
"ITEM_MOBILE_TYPE":"3",
"ITEM_INPUT_DEFAULT":"",
"ITEM_INPUT_CONFIG":""
},
{
"SERV_ID":"TS_XMGL_BMSH_SHGZ_MX",
"ITEM_CARD_WIDTH":"0",
"ITEM_LOG_FLAG":"2",
"ITEM_TIP":"",
"ITEM_ORDER_CODES":"",
"ITEM_CARD_FORMAT":"",
"ITEM_LIST_STYLE":"",
"ITEM_VALIDATE":"",
"ITEM_MEMO":"值1",
"ITEM_VALIDATE_HINT":"",
"ITEM_NOTNULL":"2",
"ITEM_LIST_ORDER":"30",
"ITEM_FIELD_TYPE":"STR",
"SAFE_HTML":"",
"ITEM_SEARCH_FLAG":"1",
"ITEM_INPUT_MODE":"1",
"ITEM_USER_FLAG":"0",
"_ROWNUM_":"3",
"EN_JSON":"",
"ITEM_LIST_WIDTH":"0",
"ITEM_EXPTENDS":"",
"ITEM_NAME":"设置参数",
"ITEM_NOTNULL_SCRIPT":"",
"ITEM_CARD_ORDER":"",
"ITEM_CARD_COLS":"1",
"ITEM_SUM_FLAG":"0",
"ITEM_TYPE":"1",
"S_MTIME":"2017-08-21 14:53:26:709",
"ITEM_LIST_FORMAT":"",
"ITEM_ID":"3bdttsdVxalWyc8EeErl",
"ITEM_LIST_FLAG":"3",
"ITEM_CARD_DISABLE":"2",
"ITEM_CARD_ROWS":"1",
"ITEM_READONLY":"2",
"ITEM_HIDDEN_SCRIPT":"",
"ITEM_LIST_EDIT":"2",
"DICT_ID":"",
"ITEM_READONLY_SCRIPT":"",
"ITEM_FIELD_LENGTH":"40",
"S_FLAG":"1",
"ITEM_CARD_LINK":"",
"ITEM_HIDDEN":"1",
"ITEM_CARD_STYLE":"",
"ITEM_UNIQUE_GROUP":"0",
"_PK_":"3bdttsdVxalWyc8EeErl",
"ITEM_LIST_ALIGN":"1",
"ITEM_INPUT_TYPE":"1",
"ITEM_LIST_LINK":"",
"ITEM_INPUT_FLAG":"2",
"ITEM_LABEL_HIDDEN":"0",
"ITEM_CODE":"MX_VALUE1",
"ITEM_MOBILE_TYPE":"3",
"ITEM_INPUT_DEFAULT":"",
"ITEM_INPUT_CONFIG":""
},
{
"SERV_ID":"TS_XMGL_BMSH_SHGZ_MX",
"ITEM_CARD_WIDTH":"0",
"ITEM_LOG_FLAG":"2",
"ITEM_TIP":"",
"ITEM_ORDER_CODES":"",
"ITEM_CARD_FORMAT":"",
"ITEM_LIST_STYLE":"",
"ITEM_VALIDATE":"",
"ITEM_MEMO":"值2",
"ITEM_VALIDATE_HINT":"",
"ITEM_NOTNULL":"2",
"ITEM_LIST_ORDER":"40",
"ITEM_FIELD_TYPE":"STR",
"SAFE_HTML":"",
"ITEM_SEARCH_FLAG":"1",
"ITEM_INPUT_MODE":"1",
"ITEM_USER_FLAG":"0",
"_ROWNUM_":"4",
"EN_JSON":"",
"ITEM_LIST_WIDTH":"0",
"ITEM_EXPTENDS":"",
"ITEM_NAME":"设置变量",
"ITEM_NOTNULL_SCRIPT":"",
"ITEM_CARD_ORDER":"",
"ITEM_CARD_COLS":"2",
"ITEM_SUM_FLAG":"0",
"ITEM_TYPE":"1",
"S_MTIME":"2017-08-21 14:53:26:833",
"ITEM_LIST_FORMAT":"",
"ITEM_ID":"0tF6VNT0kh87bh8gsDNI",
"ITEM_LIST_FLAG":"3",
"ITEM_CARD_DISABLE":"2",
"ITEM_CARD_ROWS":"1",
"ITEM_READONLY":"2",
"ITEM_HIDDEN_SCRIPT":"",
"ITEM_LIST_EDIT":"2",
"DICT_ID":"",
"ITEM_READONLY_SCRIPT":"",
"ITEM_FIELD_LENGTH":"2000",
"S_FLAG":"1",
"ITEM_CARD_LINK":"",
"ITEM_HIDDEN":"1",
"ITEM_CARD_STYLE":"",
"ITEM_UNIQUE_GROUP":"0",
"_PK_":"0tF6VNT0kh87bh8gsDNI",
"ITEM_LIST_ALIGN":"1",
"ITEM_INPUT_TYPE":"5",
"ITEM_LIST_LINK":"",
"ITEM_INPUT_FLAG":"2",
"ITEM_LABEL_HIDDEN":"0",
"ITEM_CODE":"MX_VALUE2",
"ITEM_MOBILE_TYPE":"3",
"ITEM_INPUT_DEFAULT":"",
"ITEM_INPUT_CONFIG":""
},
{
"SERV_ID":"TS_XMGL_BMSH_SHGZ_MX",
"ITEM_CARD_WIDTH":"0",
"ITEM_LOG_FLAG":"2",
"ITEM_TIP":"",
"ITEM_ORDER_CODES":"",
"ITEM_CARD_FORMAT":"",
"ITEM_LIST_STYLE":"",
"ITEM_VALIDATE":"",
"ITEM_MEMO":"实现类",
"ITEM_VALIDATE_HINT":"",
"ITEM_NOTNULL":"2",
"ITEM_LIST_ORDER":"50",
"ITEM_FIELD_TYPE":"STR",
"SAFE_HTML":"",
"ITEM_SEARCH_FLAG":"1",
"ITEM_INPUT_MODE":"1",
"ITEM_USER_FLAG":"0",
"_ROWNUM_":"5",
"EN_JSON":"",
"ITEM_LIST_WIDTH":"0",
"ITEM_EXPTENDS":"",
"ITEM_NAME":"实现类",
"ITEM_NOTNULL_SCRIPT":"",
"ITEM_CARD_ORDER":"130",
"ITEM_CARD_COLS":"2",
"ITEM_SUM_FLAG":"0",
"ITEM_TYPE":"1",
"S_MTIME":"2017-11-15 19:16:59:950",
"ITEM_LIST_FORMAT":"",
"ITEM_ID":"01OsLgImxe0GcFoHbUP8",
"ITEM_LIST_FLAG":"3",
"ITEM_CARD_DISABLE":"2",
"ITEM_CARD_ROWS":"1",
"ITEM_READONLY":"2",
"ITEM_HIDDEN_SCRIPT":"",
"ITEM_LIST_EDIT":"2",
"DICT_ID":"",
"ITEM_READONLY_SCRIPT":"",
"ITEM_FIELD_LENGTH":"100",
"S_FLAG":"1",
"ITEM_CARD_LINK":"",
"ITEM_HIDDEN":"1",
"ITEM_CARD_STYLE":"",
"ITEM_UNIQUE_GROUP":"",
"_PK_":"01OsLgImxe0GcFoHbUP8",
"ITEM_LIST_ALIGN":"1",
"ITEM_INPUT_TYPE":"1",
"ITEM_LIST_LINK":"",
"ITEM_INPUT_FLAG":"2",
"ITEM_LABEL_HIDDEN":"0",
"ITEM_CODE":"MX_IMPL",
"ITEM_MOBILE_TYPE":"3",
"ITEM_INPUT_DEFAULT":"",
"ITEM_INPUT_CONFIG":""
},
{
"SERV_ID":"TS_XMGL_BMSH_SHGZ_MX",
"ITEM_CARD_WIDTH":"0",
"ITEM_LOG_FLAG":"2",
"ITEM_TIP":"",
"ITEM_ORDER_CODES":"",
"ITEM_CARD_FORMAT":"",
"ITEM_LIST_STYLE":"",
"ITEM_VALIDATE":"",
"ITEM_MEMO":"创建者",
"ITEM_VALIDATE_HINT":"",
"ITEM_NOTNULL":"2",
"ITEM_LIST_ORDER":"50",
"ITEM_FIELD_TYPE":"STR",
"SAFE_HTML":"",
"ITEM_SEARCH_FLAG":"2",
"ITEM_INPUT_MODE":"1",
"ITEM_USER_FLAG":"0",
"_ROWNUM_":"6",
"EN_JSON":"",
"ITEM_LIST_WIDTH":"0",
"ITEM_EXPTENDS":"",
"ITEM_NAME":"创建者",
"ITEM_NOTNULL_SCRIPT":"",
"ITEM_CARD_ORDER":"",
"ITEM_CARD_COLS":"1",
"ITEM_SUM_FLAG":"0",
"ITEM_TYPE":"1",
"S_MTIME":"2017-07-28 17:32:05:617",
"ITEM_LIST_FORMAT":"",
"ITEM_ID":"27L0oSo7N4VoOZQ6WQ1s",
"ITEM_LIST_FLAG":"2",
"ITEM_CARD_DISABLE":"2",
"ITEM_CARD_ROWS":"1",
"ITEM_READONLY":"2",
"ITEM_HIDDEN_SCRIPT":"",
"ITEM_LIST_EDIT":"2",
"DICT_ID":"",
"ITEM_READONLY_SCRIPT":"",
"ITEM_FIELD_LENGTH":"40",
"S_FLAG":"1",
"ITEM_CARD_LINK":"",
"ITEM_HIDDEN":"1",
"ITEM_CARD_STYLE":"",
"ITEM_UNIQUE_GROUP":"0",
"_PK_":"27L0oSo7N4VoOZQ6WQ1s",
"ITEM_LIST_ALIGN":"1",
"ITEM_INPUT_TYPE":"1",
"ITEM_LIST_LINK":"",
"ITEM_INPUT_FLAG":"2",
"ITEM_LABEL_HIDDEN":"0",
"ITEM_CODE":"S_USER",
"ITEM_MOBILE_TYPE":"3",
"ITEM_INPUT_DEFAULT":"@USER_CODE@",
"ITEM_INPUT_CONFIG":""
},
{
"SERV_ID":"TS_XMGL_BMSH_SHGZ_MX",
"ITEM_CARD_WIDTH":"0",
"ITEM_LOG_FLAG":"2",
"ITEM_TIP":"",
"ITEM_ORDER_CODES":"",
"ITEM_CARD_FORMAT":"",
"ITEM_LIST_STYLE":"",
"ITEM_VALIDATE":"",
"ITEM_MEMO":"有效部门",
"ITEM_VALIDATE_HINT":"",
"ITEM_NOTNULL":"2",
"ITEM_LIST_ORDER":"60",
"ITEM_FIELD_TYPE":"STR",
"SAFE_HTML":"",
"ITEM_SEARCH_FLAG":"2",
"ITEM_INPUT_MODE":"1",
"ITEM_USER_FLAG":"0",
"_ROWNUM_":"7",
"EN_JSON":"",
"ITEM_LIST_WIDTH":"0",
"ITEM_EXPTENDS":"",
"ITEM_NAME":"有效部门",
"ITEM_NOTNULL_SCRIPT":"",
"ITEM_CARD_ORDER":"",
"ITEM_CARD_COLS":"1",
"ITEM_SUM_FLAG":"0",
"ITEM_TYPE":"1",
"S_MTIME":"2017-07-28 17:32:05:718",
"ITEM_LIST_FORMAT":"",
"ITEM_ID":"3uXuThtvBcqV3FwNA1ls",
"ITEM_LIST_FLAG":"2",
"ITEM_CARD_DISABLE":"2",
"ITEM_CARD_ROWS":"1",
"ITEM_READONLY":"2",
"ITEM_HIDDEN_SCRIPT":"",
"ITEM_LIST_EDIT":"2",
"DICT_ID":"",
"ITEM_READONLY_SCRIPT":"",
"ITEM_FIELD_LENGTH":"40",
"S_FLAG":"1",
"ITEM_CARD_LINK":"",
"ITEM_HIDDEN":"1",
"ITEM_CARD_STYLE":"",
"ITEM_UNIQUE_GROUP":"0",
"_PK_":"3uXuThtvBcqV3FwNA1ls",
"ITEM_LIST_ALIGN":"1",
"ITEM_INPUT_TYPE":"1",
"ITEM_LIST_LINK":"",
"ITEM_INPUT_FLAG":"2",
"ITEM_LABEL_HIDDEN":"0",
"ITEM_CODE":"S_TDEPT",
"ITEM_MOBILE_TYPE":"3",
"ITEM_INPUT_DEFAULT":"@TDEPT_CODE@",
"ITEM_INPUT_CONFIG":""
},
{
"SERV_ID":"TS_XMGL_BMSH_SHGZ_MX",
"ITEM_CARD_WIDTH":"0",
"ITEM_LOG_FLAG":"2",
"ITEM_TIP":"",
"ITEM_ORDER_CODES":"",
"ITEM_CARD_FORMAT":"",
"ITEM_LIST_STYLE":"",
"ITEM_VALIDATE":"",
"ITEM_MEMO":"有效机构",
"ITEM_VALIDATE_HINT":"",
"ITEM_NOTNULL":"2",
"ITEM_LIST_ORDER":"70",
"ITEM_FIELD_TYPE":"STR",
"SAFE_HTML":"",
"ITEM_SEARCH_FLAG":"2",
"ITEM_INPUT_MODE":"1",
"ITEM_USER_FLAG":"0",
"_ROWNUM_":"8",
"EN_JSON":"",
"ITEM_LIST_WIDTH":"0",
"ITEM_EXPTENDS":"",
"ITEM_NAME":"有效机构",
"ITEM_NOTNULL_SCRIPT":"",
"ITEM_CARD_ORDER":"",
"ITEM_CARD_COLS":"1",
"ITEM_SUM_FLAG":"0",
"ITEM_TYPE":"1",
"S_MTIME":"2017-07-28 17:32:05:798",
"ITEM_LIST_FORMAT":"",
"ITEM_ID":"1MRSQaOJqN7J88L41rpq",
"ITEM_LIST_FLAG":"2",
"ITEM_CARD_DISABLE":"2",
"ITEM_CARD_ROWS":"1",
"ITEM_READONLY":"2",
"ITEM_HIDDEN_SCRIPT":"",
"ITEM_LIST_EDIT":"2",
"DICT_ID":"",
"ITEM_READONLY_SCRIPT":"",
"ITEM_FIELD_LENGTH":"40",
"S_FLAG":"1",
"ITEM_CARD_LINK":"",
"ITEM_HIDDEN":"1",
"ITEM_CARD_STYLE":"",
"ITEM_UNIQUE_GROUP":"0",
"_PK_":"1MRSQaOJqN7J88L41rpq",
"ITEM_LIST_ALIGN":"1",
"ITEM_INPUT_TYPE":"1",
"ITEM_LIST_LINK":"",
"ITEM_INPUT_FLAG":"2",
"ITEM_LABEL_HIDDEN":"0",
"ITEM_CODE":"S_ODEPT",
"ITEM_MOBILE_TYPE":"3",
"ITEM_INPUT_DEFAULT":"@ODEPT_CODE@",
"ITEM_INPUT_CONFIG":""
},
{
"SERV_ID":"TS_XMGL_BMSH_SHGZ_MX",
"ITEM_CARD_WIDTH":"0",
"ITEM_LOG_FLAG":"2",
"ITEM_TIP":"",
"ITEM_ORDER_CODES":"",
"ITEM_CARD_FORMAT":"",
"ITEM_LIST_STYLE":"",
"ITEM_VALIDATE":"",
"ITEM_MEMO":"修改时间",
"ITEM_VALIDATE_HINT":"",
"ITEM_NOTNULL":"2",
"ITEM_LIST_ORDER":"80",
"ITEM_FIELD_TYPE":"STR",
"SAFE_HTML":"",
"ITEM_SEARCH_FLAG":"2",
"ITEM_INPUT_MODE":"1",
"ITEM_USER_FLAG":"0",
"_ROWNUM_":"9",
"EN_JSON":"",
"ITEM_LIST_WIDTH":"0",
"ITEM_EXPTENDS":"",
"ITEM_NAME":"修改时间",
"ITEM_NOTNULL_SCRIPT":"",
"ITEM_CARD_ORDER":"",
"ITEM_CARD_COLS":"1",
"ITEM_SUM_FLAG":"0",
"ITEM_TYPE":"1",
"S_MTIME":"2017-07-28 17:32:05:878",
"ITEM_LIST_FORMAT":"",
"ITEM_ID":"2Dm2aVih53pUALzVMaSa",
"ITEM_LIST_FLAG":"2",
"ITEM_CARD_DISABLE":"2",
"ITEM_CARD_ROWS":"1",
"ITEM_READONLY":"2",
"ITEM_HIDDEN_SCRIPT":"",
"ITEM_LIST_EDIT":"2",
"DICT_ID":"",
"ITEM_READONLY_SCRIPT":"",
"ITEM_FIELD_LENGTH":"40",
"S_FLAG":"1",
"ITEM_CARD_LINK":"",
"ITEM_HIDDEN":"1",
"ITEM_CARD_STYLE":"",
"ITEM_UNIQUE_GROUP":"0",
"_PK_":"2Dm2aVih53pUALzVMaSa",
"ITEM_LIST_ALIGN":"1",
"ITEM_INPUT_TYPE":"1",
"ITEM_LIST_LINK":"",
"ITEM_INPUT_FLAG":"2",
"ITEM_LABEL_HIDDEN":"0",
"ITEM_CODE":"S_MTIME",
"ITEM_MOBILE_TYPE":"3",
"ITEM_INPUT_DEFAULT":"@DATETIME_TS@",
"ITEM_INPUT_CONFIG":""
},
{
"SERV_ID":"TS_XMGL_BMSH_SHGZ_MX",
"ITEM_CARD_WIDTH":"0",
"ITEM_LOG_FLAG":"2",
"ITEM_TIP":"",
"ITEM_ORDER_CODES":"",
"ITEM_CARD_FORMAT":"",
"ITEM_LIST_STYLE":"",
"ITEM_VALIDATE":"",
"ITEM_MEMO":"有效标志",
"ITEM_VALIDATE_HINT":"",
"ITEM_NOTNULL":"2",
"ITEM_LIST_ORDER":"90",
"ITEM_FIELD_TYPE":"NUM",
"SAFE_HTML":"",
"ITEM_SEARCH_FLAG":"2",
"ITEM_INPUT_MODE":"1",
"ITEM_USER_FLAG":"0",
"_ROWNUM_":"10",
"EN_JSON":"",
"ITEM_LIST_WIDTH":"0",
"ITEM_EXPTENDS":"",
"ITEM_NAME":"有效标志",
"ITEM_NOTNULL_SCRIPT":"",
"ITEM_CARD_ORDER":"",
"ITEM_CARD_COLS":"1",
"ITEM_SUM_FLAG":"0",
"ITEM_TYPE":"1",
"S_MTIME":"2017-07-28 17:32:05:961",
"ITEM_LIST_FORMAT":"",
"ITEM_ID":"0cHib5A3J8PESrtBbG9p",
"ITEM_LIST_FLAG":"2",
"ITEM_CARD_DISABLE":"2",
"ITEM_CARD_ROWS":"1",
"ITEM_READONLY":"2",
"ITEM_HIDDEN_SCRIPT":"",
"ITEM_LIST_EDIT":"2",
"DICT_ID":"",
"ITEM_READONLY_SCRIPT":"",
"ITEM_FIELD_LENGTH":"4",
"S_FLAG":"1",
"ITEM_CARD_LINK":"",
"ITEM_HIDDEN":"1",
"ITEM_CARD_STYLE":"",
"ITEM_UNIQUE_GROUP":"0",
"_PK_":"0cHib5A3J8PESrtBbG9p",
"ITEM_LIST_ALIGN":"1",
"ITEM_INPUT_TYPE":"1",
"ITEM_LIST_LINK":"",
"ITEM_INPUT_FLAG":"2",
"ITEM_LABEL_HIDDEN":"0",
"ITEM_CODE":"S_FLAG",
"ITEM_MOBILE_TYPE":"3",
"ITEM_INPUT_DEFAULT":"1",
"ITEM_INPUT_CONFIG":""
},
{
"SERV_ID":"TS_XMGL_BMSH_SHGZ_MX",
"ITEM_CARD_WIDTH":"0",
"ITEM_LOG_FLAG":"2",
"ITEM_TIP":"",
"ITEM_ORDER_CODES":"",
"ITEM_CARD_FORMAT":"",
"ITEM_LIST_STYLE":"",
"ITEM_VALIDATE":"",
"ITEM_MEMO":"部门",
"ITEM_VALIDATE_HINT":"",
"ITEM_NOTNULL":"2",
"ITEM_LIST_ORDER":"100",
"ITEM_FIELD_TYPE":"STR",
"SAFE_HTML":"",
"ITEM_SEARCH_FLAG":"2",
"ITEM_INPUT_MODE":"1",
"ITEM_USER_FLAG":"0",
"_ROWNUM_":"11",
"EN_JSON":"",
"ITEM_LIST_WIDTH":"0",
"ITEM_EXPTENDS":"",
"ITEM_NAME":"部门",
"ITEM_NOTNULL_SCRIPT":"",
"ITEM_CARD_ORDER":"",
"ITEM_CARD_COLS":"1",
"ITEM_SUM_FLAG":"0",
"ITEM_TYPE":"1",
"S_MTIME":"2017-07-28 17:32:06:034",
"ITEM_LIST_FORMAT":"",
"ITEM_ID":"3DCN1UBHM52eokpaO7eg",
"ITEM_LIST_FLAG":"2",
"ITEM_CARD_DISABLE":"2",
"ITEM_CARD_ROWS":"1",
"ITEM_READONLY":"2",
"ITEM_HIDDEN_SCRIPT":"",
"ITEM_LIST_EDIT":"2",
"DICT_ID":"",
"ITEM_READONLY_SCRIPT":"",
"ITEM_FIELD_LENGTH":"40",
"S_FLAG":"1",
"ITEM_CARD_LINK":"",
"ITEM_HIDDEN":"1",
"ITEM_CARD_STYLE":"",
"ITEM_UNIQUE_GROUP":"0",
"_PK_":"3DCN1UBHM52eokpaO7eg",
"ITEM_LIST_ALIGN":"1",
"ITEM_INPUT_TYPE":"1",
"ITEM_LIST_LINK":"",
"ITEM_INPUT_FLAG":"2",
"ITEM_LABEL_HIDDEN":"0",
"ITEM_CODE":"S_DEPT",
"ITEM_MOBILE_TYPE":"3",
"ITEM_INPUT_DEFAULT":"@DEPT_CODE@",
"ITEM_INPUT_CONFIG":""
},
{
"SERV_ID":"TS_XMGL_BMSH_SHGZ_MX",
"ITEM_CARD_WIDTH":"0",
"ITEM_LOG_FLAG":"2",
"ITEM_TIP":"",
"ITEM_ORDER_CODES":"",
"ITEM_CARD_FORMAT":"",
"ITEM_LIST_STYLE":"",
"ITEM_VALIDATE":"",
"ITEM_MEMO":"公司",
"ITEM_VALIDATE_HINT":"",
"ITEM_NOTNULL":"2",
"ITEM_LIST_ORDER":"110",
"ITEM_FIELD_TYPE":"STR",
"SAFE_HTML":"",
"ITEM_SEARCH_FLAG":"2",
"ITEM_INPUT_MODE":"1",
"ITEM_USER_FLAG":"0",
"_ROWNUM_":"12",
"EN_JSON":"",
"ITEM_LIST_WIDTH":"0",
"ITEM_EXPTENDS":"",
"ITEM_NAME":"公司",
"ITEM_NOTNULL_SCRIPT":"",
"ITEM_CARD_ORDER":"",
"ITEM_CARD_COLS":"1",
"ITEM_SUM_FLAG":"0",
"ITEM_TYPE":"1",
"S_MTIME":"2017-07-28 17:32:06:118",
"ITEM_LIST_FORMAT":"",
"ITEM_ID":"1omFWUIMh58HI7BUnxTO",
"ITEM_LIST_FLAG":"2",
"ITEM_CARD_DISABLE":"2",
"ITEM_CARD_ROWS":"1",
"ITEM_READONLY":"2",
"ITEM_HIDDEN_SCRIPT":"",
"ITEM_LIST_EDIT":"2",
"DICT_ID":"",
"ITEM_READONLY_SCRIPT":"",
"ITEM_FIELD_LENGTH":"40",
"S_FLAG":"1",
"ITEM_CARD_LINK":"",
"ITEM_HIDDEN":"1",
"ITEM_CARD_STYLE":"",
"ITEM_UNIQUE_GROUP":"0",
"_PK_":"1omFWUIMh58HI7BUnxTO",
"ITEM_LIST_ALIGN":"1",
"ITEM_INPUT_TYPE":"1",
"ITEM_LIST_LINK":"",
"ITEM_INPUT_FLAG":"2",
"ITEM_LABEL_HIDDEN":"0",
"ITEM_CODE":"S_CMPY",
"ITEM_MOBILE_TYPE":"3",
"ITEM_INPUT_DEFAULT":"@CMPY_CODE@",
"ITEM_INPUT_CONFIG":""
},
{
"SERV_ID":"TS_XMGL_BMSH_SHGZ_MX",
"ITEM_CARD_WIDTH":"0",
"ITEM_LOG_FLAG":"2",
"ITEM_TIP":"",
"ITEM_ORDER_CODES":"",
"ITEM_CARD_FORMAT":"",
"ITEM_LIST_STYLE":"",
"ITEM_VALIDATE":"",
"ITEM_MEMO":"创建时间",
"ITEM_VALIDATE_HINT":"",
"ITEM_NOTNULL":"2",
"ITEM_LIST_ORDER":"120",
"ITEM_FIELD_TYPE":"STR",
"SAFE_HTML":"",
"ITEM_SEARCH_FLAG":"2",
"ITEM_INPUT_MODE":"1",
"ITEM_USER_FLAG":"0",
"_ROWNUM_":"13",
"EN_JSON":"",
"ITEM_LIST_WIDTH":"0",
"ITEM_EXPTENDS":"",
"ITEM_NAME":"创建时间",
"ITEM_NOTNULL_SCRIPT":"",
"ITEM_CARD_ORDER":"",
"ITEM_CARD_COLS":"1",
"ITEM_SUM_FLAG":"0",
"ITEM_TYPE":"1",
"S_MTIME":"2017-07-28 17:32:06:197",
"ITEM_LIST_FORMAT":"",
"ITEM_ID":"2HaBnID811nVDMBzizVc",
"ITEM_LIST_FLAG":"2",
"ITEM_CARD_DISABLE":"2",
"ITEM_CARD_ROWS":"1",
"ITEM_READONLY":"2",
"ITEM_HIDDEN_SCRIPT":"",
"ITEM_LIST_EDIT":"2",
"DICT_ID":"",
"ITEM_READONLY_SCRIPT":"",
"ITEM_FIELD_LENGTH":"40",
"S_FLAG":"1",
"ITEM_CARD_LINK":"",
"ITEM_HIDDEN":"1",
"ITEM_CARD_STYLE":"",
"ITEM_UNIQUE_GROUP":"0",
"_PK_":"2HaBnID811nVDMBzizVc",
"ITEM_LIST_ALIGN":"1",
"ITEM_INPUT_TYPE":"1",
"ITEM_LIST_LINK":"",
"ITEM_INPUT_FLAG":"2",
"ITEM_LABEL_HIDDEN":"0",
"ITEM_CODE":"S_ATIME",
"ITEM_MOBILE_TYPE":"3",
"ITEM_INPUT_DEFAULT":"@DATETIME_TS@",
"ITEM_INPUT_CONFIG":""
},
{
"SERV_ID":"TS_XMGL_BMSH_SHGZ_MX",
"ITEM_CARD_WIDTH":"0",
"ITEM_LOG_FLAG":"2",
"ITEM_TIP":"",
"ITEM_ORDER_CODES":"",
"ITEM_CARD_FORMAT":"",
"ITEM_LIST_STYLE":"",
"ITEM_VALIDATE":"",
"ITEM_MEMO":"项目ID",
"ITEM_VALIDATE_HINT":"",
"ITEM_NOTNULL":"2",
"ITEM_LIST_ORDER":"140",
"ITEM_FIELD_TYPE":"STR",
"SAFE_HTML":"",
"ITEM_SEARCH_FLAG":"2",
"ITEM_INPUT_MODE":"1",
"ITEM_USER_FLAG":"",
"_ROWNUM_":"14",
"EN_JSON":"",
"ITEM_LIST_WIDTH":"0",
"ITEM_EXPTENDS":"",
"ITEM_NAME":"项目ID",
"ITEM_NOTNULL_SCRIPT":"",
"ITEM_CARD_ORDER":"140",
"ITEM_CARD_COLS":"1",
"ITEM_SUM_FLAG":"",
"ITEM_TYPE":"1",
"S_MTIME":"2017-11-15 15:15:19:154",
"ITEM_LIST_FORMAT":"",
"ITEM_ID":"13LG4eOch69Xdy93yf6G",
"ITEM_LIST_FLAG":"2",
"ITEM_CARD_DISABLE":"2",
"ITEM_CARD_ROWS":"1",
"ITEM_READONLY":"2",
"ITEM_HIDDEN_SCRIPT":"",
"ITEM_LIST_EDIT":"2",
"DICT_ID":"",
"ITEM_READONLY_SCRIPT":"",
"ITEM_FIELD_LENGTH":"40",
"S_FLAG":"1",
"ITEM_CARD_LINK":"",
"ITEM_HIDDEN":"1",
"ITEM_CARD_STYLE":"",
"ITEM_UNIQUE_GROUP":"0",
"_PK_":"13LG4eOch69Xdy93yf6G",
"ITEM_LIST_ALIGN":"1",
"ITEM_INPUT_TYPE":"1",
"ITEM_LIST_LINK":"",
"ITEM_INPUT_FLAG":"2",
"ITEM_LABEL_HIDDEN":"",
"ITEM_CODE":"XM_ID",
"ITEM_MOBILE_TYPE":"3",
"ITEM_INPUT_DEFAULT":"",
"ITEM_INPUT_CONFIG":""
},
{
"SERV_ID":"TS_XMGL_BMSH_SHGZ_MX",
"ITEM_CARD_WIDTH":"0",
"ITEM_LOG_FLAG":"2",
"ITEM_TIP":"",
"ITEM_ORDER_CODES":"",
"ITEM_CARD_FORMAT":"",
"ITEM_LIST_STYLE":"",
"ITEM_VALIDATE":"",
"ITEM_MEMO":"考试群组ID",
"ITEM_VALIDATE_HINT":"",
"ITEM_NOTNULL":"2",
"ITEM_LIST_ORDER":"150",
"ITEM_FIELD_TYPE":"STR",
"SAFE_HTML":"",
"ITEM_SEARCH_FLAG":"2",
"ITEM_INPUT_MODE":"1",
"ITEM_USER_FLAG":"",
"_ROWNUM_":"15",
"EN_JSON":"",
"ITEM_LIST_WIDTH":"0",
"ITEM_EXPTENDS":"",
"ITEM_NAME":"考试群组ID",
"ITEM_NOTNULL_SCRIPT":"",
"ITEM_CARD_ORDER":"150",
"ITEM_CARD_COLS":"1",
"ITEM_SUM_FLAG":"",
"ITEM_TYPE":"1",
"S_MTIME":"2017-11-15 15:27:10:194",
"ITEM_LIST_FORMAT":"",
"ITEM_ID":"1Anj7pvZJ478bMkaJDFp",
"ITEM_LIST_FLAG":"2",
"ITEM_CARD_DISABLE":"2",
"ITEM_CARD_ROWS":"1",
"ITEM_READONLY":"2",
"ITEM_HIDDEN_SCRIPT":"",
"ITEM_LIST_EDIT":"2",
"DICT_ID":"",
"ITEM_READONLY_SCRIPT":"",
"ITEM_FIELD_LENGTH":"40",
"S_FLAG":"1",
"ITEM_CARD_LINK":"",
"ITEM_HIDDEN":"1",
"ITEM_CARD_STYLE":"",
"ITEM_UNIQUE_GROUP":"0",
"_PK_":"1Anj7pvZJ478bMkaJDFp",
"ITEM_LIST_ALIGN":"1",
"ITEM_INPUT_TYPE":"1",
"ITEM_LIST_LINK":"",
"ITEM_INPUT_FLAG":"2",
"ITEM_LABEL_HIDDEN":"",
"ITEM_CODE":"KSQZ_ID",
"ITEM_MOBILE_TYPE":"3",
"ITEM_INPUT_DEFAULT":"",
"ITEM_INPUT_CONFIG":""
},
{
"SERV_ID":"TS_XMGL_BMSH_SHGZ_MX",
"ITEM_CARD_WIDTH":"0",
"ITEM_LOG_FLAG":"2",
"ITEM_TIP":"",
"ITEM_ORDER_CODES":"",
"ITEM_CARD_FORMAT":"",
"ITEM_LIST_STYLE":"",
"ITEM_VALIDATE":"",
"ITEM_MEMO":"排序",
"ITEM_VALIDATE_HINT":"",
"ITEM_NOTNULL":"2",
"ITEM_LIST_ORDER":"160",
"ITEM_FIELD_TYPE":"NUM",
"SAFE_HTML":"",
"ITEM_SEARCH_FLAG":"2",
"ITEM_INPUT_MODE":"1",
"ITEM_USER_FLAG":"",
"_ROWNUM_":"16",
"EN_JSON":"",
"ITEM_LIST_WIDTH":"0",
"ITEM_EXPTENDS":"",
"ITEM_NAME":"排序",
"ITEM_NOTNULL_SCRIPT":"",
"ITEM_CARD_ORDER":"160",
"ITEM_CARD_COLS":"1",
"ITEM_SUM_FLAG":"",
"ITEM_TYPE":"1",
"S_MTIME":"2017-09-18 13:41:02:834",
"ITEM_LIST_FORMAT":"",
"ITEM_ID":"0ddjEPCUleMUwsCjzKwB",
"ITEM_LIST_FLAG":"2",
"ITEM_CARD_DISABLE":"2",
"ITEM_CARD_ROWS":"1",
"ITEM_READONLY":"2",
"ITEM_HIDDEN_SCRIPT":"",
"ITEM_LIST_EDIT":"2",
"DICT_ID":"",
"ITEM_READONLY_SCRIPT":"",
"ITEM_FIELD_LENGTH":"4",
"S_FLAG":"1",
"ITEM_CARD_LINK":"",
"ITEM_HIDDEN":"1",
"ITEM_CARD_STYLE":"",
"ITEM_UNIQUE_GROUP":"",
"_PK_":"0ddjEPCUleMUwsCjzKwB",
"ITEM_LIST_ALIGN":"1",
"ITEM_INPUT_TYPE":"1",
"ITEM_LIST_LINK":"",
"ITEM_INPUT_FLAG":"2",
"ITEM_LABEL_HIDDEN":"",
"ITEM_CODE":"MX_SORT",
"ITEM_MOBILE_TYPE":"3",
"ITEM_INPUT_DEFAULT":"0",
"ITEM_INPUT_CONFIG":""
},
{
"SERV_ID":"TS_XMGL_BMSH_SHGZ_MX",
"ITEM_CARD_WIDTH":"0",
"ITEM_LOG_FLAG":"2",
"ITEM_TIP":"",
"ITEM_ORDER_CODES":"",
"ITEM_CARD_FORMAT":"",
"ITEM_LIST_STYLE":"",
"ITEM_VALIDATE":"",
"ITEM_MEMO":"规则库明细mx_id",
"ITEM_VALIDATE_HINT":"",
"ITEM_NOTNULL":"2",
"ITEM_LIST_ORDER":"170",
"ITEM_FIELD_TYPE":"STR",
"SAFE_HTML":"",
"ITEM_SEARCH_FLAG":"1",
"ITEM_INPUT_MODE":"1",
"ITEM_USER_FLAG":"",
"_ROWNUM_":"17",
"EN_JSON":"",
"ITEM_LIST_WIDTH":"0",
"ITEM_EXPTENDS":"",
"ITEM_NAME":"规则库明细mx_id",
"ITEM_NOTNULL_SCRIPT":"",
"ITEM_CARD_ORDER":"170",
"ITEM_CARD_COLS":"1",
"ITEM_SUM_FLAG":"",
"ITEM_TYPE":"1",
"S_MTIME":"2017-11-16 09:57:14:717",
"ITEM_LIST_FORMAT":"",
"ITEM_ID":"3PQTTlnjJexpbOIdpZOY",
"ITEM_LIST_FLAG":"3",
"ITEM_CARD_DISABLE":"2",
"ITEM_CARD_ROWS":"1",
"ITEM_READONLY":"2",
"ITEM_HIDDEN_SCRIPT":"",
"ITEM_LIST_EDIT":"2",
"DICT_ID":"",
"ITEM_READONLY_SCRIPT":"",
"ITEM_FIELD_LENGTH":"400",
"S_FLAG":"1",
"ITEM_CARD_LINK":"",
"ITEM_HIDDEN":"1",
"ITEM_CARD_STYLE":"",
"ITEM_UNIQUE_GROUP":"",
"_PK_":"3PQTTlnjJexpbOIdpZOY",
"ITEM_LIST_ALIGN":"1",
"ITEM_INPUT_TYPE":"1",
"ITEM_LIST_LINK":"",
"ITEM_INPUT_FLAG":"2",
"ITEM_LABEL_HIDDEN":"",
"ITEM_CODE":"GZK_MX_ID",
"ITEM_MOBILE_TYPE":"3",
"ITEM_INPUT_DEFAULT":"",
"ITEM_INPUT_CONFIG":""
},
{
"SERV_ID":"TS_XMGL_BMSH_SHGZ_MX",
"ITEM_CARD_WIDTH":"0",
"ITEM_LOG_FLAG":"2",
"ITEM_TIP":"",
"ITEM_ORDER_CODES":"",
"ITEM_CARD_FORMAT":"",
"ITEM_LIST_STYLE":"",
"ITEM_VALIDATE":"",
"ITEM_MEMO":"",
"ITEM_VALIDATE_HINT":"",
"ITEM_NOTNULL":"2",
"ITEM_LIST_ORDER":"999",
"ITEM_FIELD_TYPE":"STR",
"SAFE_HTML":"",
"ITEM_SEARCH_FLAG":"1",
"ITEM_INPUT_MODE":"1",
"ITEM_USER_FLAG":"2",
"_ROWNUM_":"18",
"EN_JSON":"",
"ITEM_LIST_WIDTH":"100",
"ITEM_EXPTENDS":"",
"ITEM_NAME":"设置",
"ITEM_NOTNULL_SCRIPT":"",
"ITEM_CARD_ORDER":"",
"ITEM_CARD_COLS":"1",
"ITEM_SUM_FLAG":"2",
"ITEM_TYPE":"3",
"S_MTIME":"2017-11-14 13:06:49:816",
"ITEM_LIST_FORMAT":"",
"ITEM_ID":"3NmDTTzAhfKH3SpiDUHE",
"ITEM_LIST_FLAG":"1",
"ITEM_CARD_DISABLE":"2",
"ITEM_CARD_ROWS":"1",
"ITEM_READONLY":"2",
"ITEM_HIDDEN_SCRIPT":"",
"ITEM_LIST_EDIT":"2",
"DICT_ID":"",
"ITEM_READONLY_SCRIPT":"",
"ITEM_FIELD_LENGTH":"40",
"S_FLAG":"1",
"ITEM_CARD_LINK":"",
"ITEM_HIDDEN":"1",
"ITEM_CARD_STYLE":"",
"ITEM_UNIQUE_GROUP":"0",
"_PK_":"3NmDTTzAhfKH3SpiDUHE",
"ITEM_LIST_ALIGN":"1",
"ITEM_INPUT_TYPE":"1",
"ITEM_LIST_LINK":"",
"ITEM_INPUT_FLAG":"2",
"ITEM_LABEL_HIDDEN":"2",
"ITEM_CODE":"BUTTONS",
"ITEM_MOBILE_TYPE":"3",
"ITEM_INPUT_DEFAULT":"",
"ITEM_INPUT_CONFIG":""
}
],
"SERV_CACHE_FLAG":"3",
"_PK_":"TS_XMGL_BMSH_SHGZ_MX",
"SERV_LIST_LOAD":"1",
"S_CMPY":"icbc",
"SERV_DATA_CODE":"",
"SERV_DICT_CACHE":"",
"SERV_CARD_TMPL_CODES":"",
"SY_SERV_WHERE":
[
]
}